CHANGES.rst
DESCRIPTION.rst
LICENSE
MANIFEST.in
README.md
setup.py
src/wai.annotations.imgvis.egg-info/PKG-INFO
src/wai.annotations.imgvis.egg-info/SOURCES.txt
src/wai.annotations.imgvis.egg-info/dependency_links.txt
src/wai.annotations.imgvis.egg-info/entry_points.txt
src/wai.annotations.imgvis.egg-info/namespace_packages.txt
src/wai.annotations.imgvis.egg-info/requires.txt
src/wai.annotations.imgvis.egg-info/top_level.txt
src/wai/annotations/imgvis/isp/__init__.py
src/wai/annotations/imgvis/isp/annotation_overlay/__init__.py
src/wai/annotations/imgvis/isp/annotation_overlay/component/_AnnotationOverlayIC.py
src/wai/annotations/imgvis/isp/annotation_overlay/component/_AnnotationOverlayIS.py
src/wai/annotations/imgvis/isp/annotation_overlay/component/_AnnotationOverlayOD.py
src/wai/annotations/imgvis/isp/annotation_overlay/component/__init__.py
src/wai/annotations/imgvis/isp/annotation_overlay/component/_colors.py
src/wai/annotations/imgvis/isp/annotation_overlay/component/_fonts.py
src/wai/annotations/imgvis/isp/annotation_overlay/specifier/_AnnotationOverlayICISPSpecifier.py
src/wai/annotations/imgvis/isp/annotation_overlay/specifier/_AnnotationOverlayISISPSpecifier.py
src/wai/annotations/imgvis/isp/annotation_overlay/specifier/_AnnotationOverlayODISPSpecifier.py
src/wai/annotations/imgvis/isp/annotation_overlay/specifier/__init__.py
src/wai/annotations/imgvis/isp/combine_annotations/__init__.py
src/wai/annotations/imgvis/isp/combine_annotations/component/_CombineAnnotationsOD.py
src/wai/annotations/imgvis/isp/combine_annotations/component/__init__.py
src/wai/annotations/imgvis/isp/combine_annotations/specifier/_CombineAnnotationsODISPSpecifier.py
src/wai/annotations/imgvis/isp/combine_annotations/specifier/__init__.py
src/wai/annotations/imgvis/sink/__init__.py
src/wai/annotations/imgvis/sink/annotation_overlay/__init__.py
src/wai/annotations/imgvis/sink/annotation_overlay/component/_AnnotationOverlay.py
src/wai/annotations/imgvis/sink/annotation_overlay/component/__init__.py
src/wai/annotations/imgvis/sink/annotation_overlay/specifier/_AnnotationOverlayODOutputFormatSpecifier.py
src/wai/annotations/imgvis/sink/annotation_overlay/specifier/__init__.py
src/wai/annotations/imgvis/sink/image_viewer/__init__.py
src/wai/annotations/imgvis/sink/image_viewer/component/_ImageViewer.py
