Metadata-Version: 2.1
Name: wai.annotations.imgvis
Version: 1.0.3
Summary: Image visualization plugins for wai.annotations.
Home-page: https://github.com/waikato-ufdl/wai-annotations-imgvis
Author: Peter Reutemann
Author-email: fracpete@waikato.ac.nz
License: Apache License Version 2.0
Platform: UNKNOWN
Classifier: Development Status :: 4 - Beta
Classifier: License :: OSI Approved :: Apache Software License
Classifier: Topic :: Scientific/Engineering :: Mathematics
Classifier: Programming Language :: Python :: 3
License-File: LICENSE
